{"name":"Python","tagline":"","body":"# template for \"Guess the number\" mini-project\r\n# input will come from buttons and an input field\r\n# all output for the game will be printed in the console\r\n\r\nimport simplegui\r\nimport random\r\nimport math\r\n\r\n# initialize global variables used in your code\r\nnum_range = 100\r\nsecret_num = 0\r\nguesses_left = 0\r\n\r\n\r\n# helper function to start and restart the game\r\ndef new_game():  \r\n    global num_range\r\n    global secret_num\r\n    global guesses_left\r\n    \r\n    secret_num = random.randrange(0, num_range)\r\n    \r\n    if num_range == 100 : \t\r\n        guesses_left = 7\r\n    elif num_range == 1000 :\r\n        guesses_left = 10\r\n      \r\n\r\n    print \"Start game. The range is from 0 to \", num_range, \". Hope you can!\"\r\n    print \"Number of remaining guesses is \", guesses_left, \"\\n\"\r\n    pass\r\n\r\n\r\n# define event handlers for control panel\r\ndef range100():\r\n    global num_range\r\n    num_range = 100 \r\n    new_game() \r\n    \r\n\r\ndef range1000():\r\n    global num_range\r\n    num_range = 1000 \r\n    new_game()\r\n    \r\n\r\n    \r\ndef input_guess(guess):    \r\n    # main game logic goes here\t\r\n    global guesses_left\r\n    global secret_num \r\n    \r\n    won = False\r\n    \r\n    print \"You guessed: \",guess\r\n    guesses_left = guesses_left - 1\r\n    print \"Number of remaining guesses is \", guesses_left\r\n    \r\n    if int(guess) == secret_num:       \r\n        won = True\r\n    elif int(guess) > secret_num:\r\n        result = \"Lower!\"\r\n    else:\r\n        result = \"Higher!\"                \r\n        \r\n        \r\n    if won:\r\n        print \"That is correct!You won!\\n\"\r\n        new_game()\r\n        return\r\n    elif guesses_left == 0:\r\n        print \"Be optimist and try again!\"   \r\n        new_game()\r\n        return\r\n    else:\r\n        print result\r\n        \r\n            \r\n    \r\n# create frame\r\nframe = simplegui.create_frame(\"Game: Guess the number!\", 250, 250)\r\nframe.set_canvas_background('Blue')\r\n\r\n# register event handlers for control elements\r\nframe.add_button(\"Range is [0, 100)\", range100, 100)\r\nframe.add_button(\"Range is [0, 1000)\", range1000, 100)\t\r\nframe.add_input(\"Enter your guess\", input_guess, 100)\r\n\r\n# call new_game and start frame\r\nnew_game()\r\nframe.start()\r\n\r\n\r\n\r\n# always remember to check your completed program against the grading rubric","google":"","note":"Don't delete this file! It's used internally to help with page regeneration."}